fastapi_zitadel_auth/__init__.py
fastapi_zitadel_auth/auth.py
fastapi_zitadel_auth/exceptions.py
fastapi_zitadel_auth/openid_config.py
fastapi_zitadel_auth/py.typed
fastapi_zitadel_auth/token.py
fastapi_zitadel_auth/user.py
fastapi_zitadel_auth-0.3.0.dist-info/METADATA
fastapi_zitadel_auth-0.3.0.dist-info/WHEEL
fastapi_zitadel_auth-0.3.0.dist-info/RECORD
