Metadata-Version: 2.4
Name: fastapi-zitadel-auth
Version: 0.3.0
Summary: Zitadel authentication for FastAPI
Author-email: Clean Energy Exchange <info@ceex.ch>
License-Expression: MIT
Keywords: async,asyncio,authentication,fastapi,oauth,oidc,zitadel
Classifier: Development Status :: 4 - Beta
Classifier: Environment :: Web Environment
Classifier: Intended Audience :: Developers
Classifier: Operating System :: OS Independent
Classifier: Programming Language :: Python
Classifier: Programming Language :: Python :: 3.10
Classifier: Programming Language :: Python :: 3.11
Classifier: Programming Language :: Python :: 3.12
Classifier: Programming Language :: Python :: 3.13
Classifier: Programming Language :: Python :: 3.14
Classifier: Topic :: Software Development
Classifier: Topic :: Software Development :: Libraries
Classifier: Topic :: Software Development :: Libraries :: Application Frameworks
Classifier: Topic :: Software Development :: Libraries :: Python Modules
Requires-Python: >=3.10
Requires-Dist: cryptography>=43.0.3
Requires-Dist: fastapi>=0.115.4
Requires-Dist: httpx[http2]>=0.27.2
Requires-Dist: pyjwt>=2.9.0
